giza_actions/__init__.py
giza_actions/action.py
giza_actions/agent.py
giza_actions/deployments.py
giza_actions/logger.py
giza_actions/logging.yaml
giza_actions/model.py
giza_actions/task.py
giza_actions/utils.py
giza_actions-0.3.2.dist-info/LICENSE
giza_actions-0.3.2.dist-info/METADATA
giza_actions-0.3.2.dist-info/WHEEL
giza_actions-0.3.2.dist-info/RECORD
