Metadata-Version: 2.1
Name: giza-actions
Version: 0.3.2
Summary: A Python SDK for Giza platform
License: MIT
Author: Francisco Algaba
Author-email: fran@gizatech.xyz
Requires-Python: >=3.11,<4.0
Classifier: License :: OSI Approved :: MIT License
Classifier: Programming Language :: Python :: 3
Classifier: Programming Language :: Python :: 3.11
Classifier: Programming Language :: Python :: 3.12
Provides-Extra: agents
Requires-Dist: ape-etherscan (>=0.7.2,<0.8.0) ; extra == "agents"
Requires-Dist: diskcache (>=5.6.3,<6.0.0)
Requires-Dist: distlib (>=0.3.8,<0.4.0)
Requires-Dist: eth-ape (>=0.7.10,<0.8.0) ; extra == "agents"
Requires-Dist: giza-cli (>=0.15.0,<1.0.0)
Requires-Dist: giza-osiris (>=0.2.8,<1.0.0)
Requires-Dist: httpx (>=0.25.1,<0.26.0)
Requires-Dist: loguru (>=0.7.2,<0.8.0)
Requires-Dist: numpy (>=1.26.2,<2.0.0)
Requires-Dist: onnx (>=1.15.0,<2.0.0)
Requires-Dist: onnxruntime (>=1.16.3,<2.0.0)
Requires-Dist: prefect (==2.14.6)
Requires-Dist: prefect-docker (>=0.4.1,<0.5.0)
Requires-Dist: prefect-gcp (>=0.5.4,<0.6.0)
Requires-Dist: pyyaml (>=6.0.1,<7.0.0)
